qulearn/__init__.py
qulearn/datagen.py
qulearn/fat.py
qulearn/fim.py
qulearn/hat_basis.py
qulearn/loss.py
qulearn/memory.py
qulearn/mps.py
qulearn/mps_kronprod.py
qulearn/observable.py
qulearn/qkernel.py
qulearn/qlayer.py
qulearn/rademacher.py
qulearn/trainer.py
qulearn/types.py
qulearn/utils.py
qulearn-0.8.2.dist-info/LICENSE
qulearn-0.8.2.dist-info/METADATA
qulearn-0.8.2.dist-info/WHEEL
qulearn-0.8.2.dist-info/RECORD
