Metadata-Version: 2.3
Name: qulearn
Version: 0.8.2
Summary: Streamlining quantum and classical machine learning model development.
Author: Mazen Ali
Author-email: mazen.ali90@gmail.com
Requires-Python: >=3.9,<3.12
Classifier: Programming Language :: Python :: 3
Classifier: Programming Language :: Python :: 3.9
Classifier: Programming Language :: Python :: 3.10
Classifier: Programming Language :: Python :: 3.11
Requires-Dist: ipywidgets (==7.7.1)
Requires-Dist: matplotlib (>=3.6.3,<4.0.0)
Requires-Dist: pennylane (>=0.28.0,<0.29.0)
Requires-Dist: pennylane-lightning (>=0.29.0,<0.30.0)
Requires-Dist: protobuf (==4.23.0)
Requires-Dist: pydoe (>=0.3.8,<0.4.0)
Requires-Dist: pythreejs (>=2.4.1,<3.0.0)
Requires-Dist: pyyaml (>=6.0,<7.0)
Requires-Dist: scikit-learn (>=1.3.2,<2.0.0)
Requires-Dist: scipy (>=1.11.1,<2.0.0)
Requires-Dist: tensorflow (>=2.12.0,<3.0.0)
Requires-Dist: tntorch (>=1.1.1,<2.0.0)
Requires-Dist: torch (==2.0)
Requires-Dist: torch-tb-profiler (>=0.4.1,<0.5.0)
Requires-Dist: torchmetrics (>=1.2.0,<2.0.0)
Requires-Dist: torchviz (>=0.0.2,<0.0.3)
Project-URL: Documentation, https://qulearn.readthedocs.io/
Project-URL: Homepage, https://github.com/MazenAli/QuLearn
Project-URL: Repository, https://github.com/MazenAli/QuLearn
